adminlte/Assets.py
adminlte/__init__.py
adminlte/admin.py
adminlte/apps.py
adminlte/forms.py
adminlte/static/favicon.ico
adminlte/static/admin/css/base.css
adminlte/static/admin/css/changelists.css
adminlte/static/admin/css/dashboard.css
adminlte/static/admin/css/fonts.css
adminlte/static/admin/css/forms.css
adminlte/static/admin/css/login.css
adminlte/static/admin/css/rtl.css
adminlte/static/admin/css/widgets.css
adminlte/static/admin/fonts/LICENSE.txt
adminlte/static/admin/fonts/LICENSE.txt.py
adminlte/static/admin/fonts/README.txt
adminlte/static/admin/fonts/README.txt.py
adminlte/static/admin/fonts/Roboto-Bold-webfont.woff
adminlte/static/admin/fonts/Roboto-Light-webfont.woff
adminlte/static/admin/fonts/Roboto-Regular-webfont.woff
adminlte/static/admin/img/LICENSE
adminlte/static/admin/img/README.txt
adminlte/static/admin/img/README.txt.py
adminlte/static/admin/img/calendar-icons.svg
adminlte/static/admin/img/icon-addlink.svg
adminlte/static/admin/img/icon-alert.svg
adminlte/static/admin/img/icon-calendar.svg
adminlte/static/admin/img/icon-changelink.svg
adminlte/static/admin/img/icon-clock.svg
adminlte/static/admin/img/icon-deletelink.svg
adminlte/static/admin/img/icon-no.svg
adminlte/static/admin/img/icon-unknown-alt.svg
adminlte/static/admin/img/icon-unknown.svg
adminlte/static/admin/img/icon-yes.svg
adminlte/static/admin/img/inline-delete.svg
adminlte/static/admin/img/search.svg
adminlte/static/admin/img/selector-icons.svg
adminlte/static/admin/img/sorting-icons.svg
adminlte/static/admin/img/tooltag-add.svg
adminlte/static/admin/img/tooltag-arrowright.svg
adminlte/static/admin/img/gis/move_vertex_off.svg
adminlte/static/admin/img/gis/move_vertex_on.svg
adminlte/static/admin/js/SelectBox.js
adminlte/static/admin/js/SelectFilter2.js
adminlte/static/admin/js/actions.js
adminlte/static/admin/js/actions.min.js
adminlte/static/admin/js/calendar.js
adminlte/static/admin/js/cancel.js
django_adminlte_x-0.22.1.dist-info/DESCRIPTION.rst
django_adminlte_x-0.22.1.dist-info/METADATA
django_adminlte_x-0.22.1.dist-info/RECORD
django_adminlte_x-0.22.1.dist-info/WHEEL
django_adminlte_x-0.22.1.dist-info/metadata.json
django_adminlte_x-0.22.1.dist-info/top_level.txt
