Metadata-Version: 2.0
Name: django-adminlte-x
Version: 0.22.1
Summary: AdminLTE Bootstrap Theme packaged for Django
Home-page: https://github.com/dnaextrim/django_adminlte_x
Author: Dony Wahyu Isprananda
Author-email: dna.extrim@gmail.com
License: MIT License
Keywords: django bootstrap adminlte theme
Platform: UNKNOWN
Classifier: Development Status :: 5 - Production/Stable
Classifier: Environment :: Web Environment
Classifier: Framework :: Django
Classifier: Framework :: Django :: 1.9
Classifier: Framework :: Django :: 1.10
Classifier: Intended Audience :: Developers
Classifier: License :: OSI Approved :: BSD License
Classifier: Operating System :: OS Independent
Classifier: Programming Language :: Python
Classifier: Programming Language :: Python :: 3
Classifier: Programming Language :: Python :: 3.4
Classifier: Programming Language :: Python :: 3.5
Classifier: Topic :: Internet :: WWW/HTTP
Classifier: Topic :: Internet :: WWW/HTTP :: Dynamic Content
Requires-Dist: django-appconf (>=0.6.0)
